tests/__init__.py
tests/test_datasets.py
tests/test_models.py
torch_enhance/__init__.py
torch_enhance/metrics.py
torch_enhance/utils.py
torch_enhance/datasets/__init__.py
torch_enhance/datasets/base.py
torch_enhance/datasets/bsds100.py
torch_enhance/datasets/bsds200.py
torch_enhance/datasets/bsds300.py
torch_enhance/datasets/bsds500.py
torch_enhance/datasets/div2k.py
torch_enhance/datasets/general100.py
torch_enhance/datasets/historical.py
torch_enhance/datasets/manga109.py
torch_enhance/datasets/set14.py
torch_enhance/datasets/set5.py
torch_enhance/datasets/t91.py
torch_enhance/datasets/urban100.py
torch_enhance/losses/__init__.py
torch_enhance/losses/vgg.py
torch_enhance/models/__init__.py
torch_enhance/models/base.py
torch_enhance/models/baseline.py
torch_enhance/models/edsr.py
torch_enhance/models/espcn.py
torch_enhance/models/srcnn.py
torch_enhance/models/srresnet.py
torch_enhance/models/vdsr.py
torch_enhance-0.1.8.dist-info/LICENSE
torch_enhance-0.1.8.dist-info/METADATA
torch_enhance-0.1.8.dist-info/WHEEL
torch_enhance-0.1.8.dist-info/top_level.txt
torch_enhance-0.1.8.dist-info/RECORD
